any_urlfield/__init__.py
any_urlfield/cache.py
any_urlfield/registry.py
any_urlfield/validators.py
any_urlfield/forms/__init__.py
any_urlfield/forms/fields.py
any_urlfield/forms/widgets.py
any_urlfield/locale/nl/LC_MESSAGES/django.mo
any_urlfield/locale/nl/LC_MESSAGES/django.po
any_urlfield/models/__init__.py
any_urlfield/models/fields.py
any_urlfield/models/values.py
any_urlfield/static/any_urlfield/any_urlfield.css
any_urlfield/static/any_urlfield/any_urlfield.js
any_urlfield/templates/any_urlfield/widgets/any_urlfield.html
any_urlfield/templates/any_urlfield/widgets/url_type_select.html
any_urlfield/templatetags/__init__.py
any_urlfield/templatetags/any_urlfield_tags.py
any_urlfield/tests/__init__.py
any_urlfield/tests/test_forms.py
any_urlfield/tests/test_models.py
any_urlfield/tests/test_pickle.py
any_urlfield/tests/test_serializers.py
any_urlfield/tests/test_validation.py
any_urlfield/tests/urls.py
any_urlfield/tests/utils.py
django_any_urlfield-2.7.post1.dist-info/AUTHORS
django_any_urlfield-2.7.post1.dist-info/LICENSE
django_any_urlfield-2.7.post1.dist-info/METADATA
django_any_urlfield-2.7.post1.dist-info/WHEEL
django_any_urlfield-2.7.post1.dist-info/top_level.txt
django_any_urlfield-2.7.post1.dist-info/RECORD
